[{"scoreTime": "Tuesday 11/07 at 12:29 PM", "projTime": "Monday 11/06 at 06:16 PM"}, {"owner": "Scott", "data": [{"Slot": "QB", "player": "Kirk Cousins", "pts": 8.3, "proj": 14.6}, {"Slot": "RB", "player": "Ezekiel Elliott & Alvin Kamara", "pts": 40.5, "proj": 31.1}, {"Slot": "WR", "player": "A.J. Green & Will Fuller V", "pts": 3.8000000000000003, "proj": 17.200000000000003}, {"Slot": "TE", "player": "Jimmy Graham", "pts": 5.9, "proj": 8.1}, {"Slot": "K", "player": "Greg Zuerlein", "pts": 17.0, "proj": 9.3}, {"Slot": "D/ST", "player": "Texans", "pts": 10.0, "proj": 8.5}, {"Slot": "FLEX", "player": "Christian McCaffrey", "pts": 15.4, "proj": 9.9}]}, {"owner": "Chase", "data": [{"Slot": "QB", "player": "Drew Brees", "pts": 18.7, "proj": 19.7}, {"Slot": "RB", "player": "Jonathan Stewart & Derrick Henry", "pts": 7.699999999999999, "proj": 15.600000000000001}, {"Slot": "WR", "player": "Demaryius Thomas & Sammy Watkins", "pts": 25.7, "proj": 13.5}, {"Slot": "TE", "player": "Jared Cook", "pts": 12.6, "proj": 5.9}, {"Slot": "K", "player": "Justin Tucker", "pts": 9.0, "proj": 8.8}, {"Slot": "D/ST", "player": "Bengals", "pts": -1.0, "proj": 6.4}, {"Slot": "FLEX", "player": "Mohamed Sanu", "pts": 8.3, "proj": 6.0}]}, {"owner": "Adam", "data": [{"Slot": "QB", "player": "Jameis Winston", "pts": 3.5, "proj": 17.5}, {"Slot": "RB", "player": "Ameer Abdullah & C.J. Anderson", "pts": 11.0, "proj": 15.3}, {"Slot": "WR", "player": "Mike Evans & Michael Crabtree", "pts": 5.3, "proj": 18.4}, {"Slot": "TE", "player": "Austin Hooper", "pts": 3.6, "proj": 3.8}, {"Slot": "K", "player": "Wil Lutz", "pts": 6.0, "proj": 9.2}, {"Slot": "D/ST", "player": "Jaguars", "pts": 14.0, "proj": 9.2}, {"Slot": "FLEX", "player": "Carlos Hyde", "pts": 12.5, "proj": 12.9}]}, {"owner": "Michael", "data": [{"Slot": "QB", "player": "Russell Wilson", "pts": 23.6, "proj": 19.8}, {"Slot": "RB", "player": "LeSean McCoy & Devonta Freeman", "pts": 8.9, "proj": 27.5}, {"Slot": "WR", "player": "Doug Baldwin & Alshon Jeffery", "pts": 37.2, "proj": 18.8}, {"Slot": "TE", "player": "Evan Engram", "pts": 13.0, "proj": 7.6}, {"Slot": "K", "player": "Matt Bryant", "pts": 7.0, "proj": 8.2}, {"Slot": "D/ST", "player": "Rams", "pts": 11.0, "proj": 6.2}, {"Slot": "FLEX", "player": "LeGarrette Blount", "pts": 3.7, "proj": 8.5}]}, {"owner": "Wyatt", "data": [{"Slot": "QB", "player": "Alex Smith", "pts": 18.4, "proj": 18.3}, {"Slot": "RB", "player": "Leonard Fournette & Lamar Miller", "pts": 9.1, "proj": 13.8}, {"Slot": "WR", "player": "Tyreek Hill & Dez Bryant", "pts": 20.6, "proj": 19.9}, {"Slot": "TE", "player": "Zach Ertz", "pts": 0.0, "proj": 0.0}, {"Slot": "K", "player": "Adam Vinatieri", "pts": 10.0, "proj": 7.4}, {"Slot": "D/ST", "player": "Panthers", "pts": 4.0, "proj": 5.8}, {"Slot": "FLEX", "player": "Jarvis Landry", "pts": 9.2, "proj": 8.1}]}, {"owner": "David", "data": [{"Slot": "QB", "player": "Matt Ryan", "pts": 18.4, "proj": 13.8}, {"Slot": "RB", "player": "Todd Gurley II & Chris Thompson", "pts": 25.5, "proj": 24.8}, {"Slot": "WR", "player": "Larry Fitzgerald & Golden Tate", "pts": 18.3, "proj": 14.2}, {"Slot": "TE", "player": "Cameron Brate", "pts": 0.9, "proj": 6.9}, {"Slot": "K", "player": "Jake Elliott", "pts": 10.0, "proj": 9.8}, {"Slot": "D/ST", "player": "Eagles", "pts": 10.0, "proj": 9.5}, {"Slot": "FLEX", "player": "DeMarco Murray", "pts": 4.1, "proj": 10.5}]}, {"owner": "Petr", "data": [{"Slot": "QB", "player": "Tyrod Taylor", "pts": 26.9, "proj": 17.0}, {"Slot": "RB", "player": "Kareem Hunt & Mark Ingram", "pts": 14.0, "proj": 30.799999999999997}, {"Slot": "WR", "player": "Julio Jones & Amari Cooper", "pts": 17.6, "proj": 16.799999999999997}, {"Slot": "TE", "player": "Travis Kelce", "pts": 13.3, "proj": 9.3}, {"Slot": "K", "player": "Harrison Butker", "pts": 5.0, "proj": 8.8}, {"Slot": "D/ST", "player": "Lions", "pts": 6.0, "proj": 8.4}, {"Slot": "FLEX", "player": "Doug Martin", "pts": 0.7, "proj": 11.4}]}, {"owner": "Samir", "data": [{"Slot": "QB", "player": "Dak Prescott", "pts": 26.7, "proj": 20.0}, {"Slot": "RB", "player": "Marshawn Lynch & Tevin Coleman", "pts": 26.700000000000003, "proj": 16.3}, {"Slot": "WR", "player": "Michael Thomas & DeAndre Hopkins", "pts": 21.1, "proj": 23.1}, {"Slot": "TE", "player": "Jason Witten", "pts": 0.5, "proj": 6.4}, {"Slot": "K", "player": "Ryan Succop", "pts": 6.0, "proj": 10.1}, {"Slot": "D/ST", "player": "Broncos", "pts": 2.0, "proj": 6.5}, {"Slot": "FLEX", "player": "Aaron Jones", "pts": 1.1, "proj": 11.0}]}]